        {
            "type": "Fan",
            "displayName": "Master Fan",
            "on": "FALSE",
            "rotationSpeed": 25,
            "name": "Master Fan",
            "manufacturer": "OLIBRA",
            "model": "BD-1000",
            "serialNumber": "ZZEJ51347",
            "queue": "BBA",
            "polling": [
                {
                    "characteristic": "on"
                },
                {
                    "characteristic": "rotationSpeed"
                }
            ],
            "props": {
                "brightness": {
                    "minStep": 14
                }
            },
            "state_cmd": "'/usr/local/lib/node_modules/homebridge-cmd4-bondbridge/BondBridge.sh'",
            "state_cmd_suffix": "fan 'token:df60c5b500bcd518' 'device:0d3a13c2' ${BBIP}"
        },
        {
            "type": "Lightbulb",
            "displayName": "Master Fan Timer",
            "on": "FALSE",
            "brightness": 0,
            "name": "Master Fan Timer",
            "manufacturer": "OLIBRA",
            "model": "BD-1000",
            "serialNumber": "ZZEJ51347",
            "queue": "BBA",
            "polling": [
                {
                    "characteristic": "on"
                },
                {
                    "characteristic": "brightness"
                }
            ],
            "props": {
                "brightness": {
                    "minStep": 1
                }
            },
            "state_cmd": "'/usr/local/lib/node_modules/homebridge-cmd4-bondbridge/BondBridge.sh'",
            "state_cmd_suffix": "fanTimer 'token:df60c5b500bcd518' 'device:2c31a3d0' 'fanDevice:0d3a13c2' ${BBIP}"
        },
        {
            "type": "Lightbulb",
            "displayName": "Master Light",
            "on": "FALSE",
            "brightness": 25,
            "name": "Master Light",
            "manufacturer": "OLIBRA",
            "model": "BD-1000",
            "serialNumber": "ZZEJ51347",
            "queue": "BBA",
            "polling": [
                {
                    "characteristic": "on"
                },
                {
                    "characteristic": "brightness"
                }
            ],
            "props": {
                "brightness": {
                    "minStep": 14
                }
            },
            "state_cmd": "'/usr/local/lib/node_modules/homebridge-cmd4-bondbridge/BondBridge.sh'",
            "state_cmd_suffix": "light 'token:df60c5b500bcd518' 'device:406eb9b1' ${BBIP}"
        },
        {
            "type": "Lightbulb",
            "displayName": "Master Light Timer",
            "on": "FALSE",
            "brightness": 0,
            "name": "Master Light Timer",
            "manufacturer": "OLIBRA",
            "model": "BD-1000",
            "serialNumber": "ZZEJ51347",
            "queue": "BBA",
            "polling": [
                {
                    "characteristic": "on"
                },
                {
                    "characteristic": "brightness"
                }
            ],
            "props": {
                "brightness": {
                    "minStep": 1
                }
            },
            "state_cmd": "'/usr/local/lib/node_modules/homebridge-cmd4-bondbridge/BondBridge.sh'",
            "state_cmd_suffix": "lightTimer 'token:df60c5b500bcd518' 'device:1b9be604' 'lightDevice:406eb9b1' ${BBIP}"
        }
